ormedian_resizer/__init__.py
ormedian_resizer/resize_imgs.py
ormedian_resizer-0.0.1.4.dist-info/METADATA
ormedian_resizer-0.0.1.4.dist-info/WHEEL
ormedian_resizer-0.0.1.4.dist-info/entry_points.txt
ormedian_resizer-0.0.1.4.dist-info/license_files/LICENSE
ormedian_resizer-0.0.1.4.dist-info/RECORD
