Metadata-Version: 2.1
Name: ormedian-resizer
Version: 0.0.1.4
Project-URL: Homepage, https://github.com/exponentialR/ormedian-resizer
Author-email: Samuel Adebayo <samuel@ormedian.com>
Keywords: image,image resizer,jpg,png,reduce image quality,reduce size
Classifier: License :: OSI Approved :: MIT License
Classifier: Programming Language :: Python
Classifier: Programming Language :: Python :: 3
Requires-Python: >=3.6
Requires-Dist: matplotlib>=3.0.0
Requires-Dist: pillow>=8.4.0
